{
    "object_key": [
        28,
        38,
        42
    ],
    "bbox": [
        [
            316.8533020019531,
            0.0,
            381.4306335449219,
            153.91346740722656
        ],
        [
            456.8302917480469,
            94.92656707763672,
            492.600341796875,
            110.09640502929688
        ],
        [
            384.85546875,
            101.66559600830078,
            442.0983581542969,
            171.06271362304688
        ]
    ],
    "score": [
        0.721040666103363,
        0.8232582211494446,
        0.9881662130355835
    ],
    "label": [
        62,
        64,
        66
    ],
    "image_path": "rgbd_dataset_freiburg3_long_office_household/rgb/1341848030.894711.png",
    "image_key": 1488,
    "pose": [
        -2.8896,
        -0.5011,
        1.3639,
        0.6719,
        -0.5743,
        0.2723,
        -0.3801
    ]
}