{
    "object_key": [
        20
    ],
    "bbox": [
        [
            158.0916748046875,
            0.0,
            556.9376831054688,
            480.0
        ]
    ],
    "score": [
        0.976643979549408
    ],
    "label": [
        77
    ],
    "image_path": "rgbd_dataset_freiburg3_long_office_household/rgb/1341848016.353746.png",
    "image_key": 1059,
    "pose": [
        -1.0451,
        -1.0644,
        1.2122,
        0.5956,
        0.6828,
        -0.3011,
        -0.2973
    ]
}