{
    "object_key": [
        3,
        5,
        7,
        11
    ],
    "bbox": [
        [
            338.6462097167969,
            28.365781784057617,
            391.4537658691406,
            141.6486053466797
        ],
        [
            313.09100341796875,
            15.254956245422363,
            356.5158996582031,
            137.3303680419922
        ],
        [
            490.3049621582031,
            48.98828125,
            571.8619995117188,
            200.6741180419922
        ],
        [
            522.5016479492188,
            231.75209045410156,
            582.4418334960938,
            332.6946716308594
        ]
    ],
    "score": [
        0.8770470023155212,
        0.8677240610122681,
        0.6087833046913147,
        0.568694531917572
    ],
    "label": [
        39,
        39,
        39,
        39
    ],
    "image_path": "rgbd_dataset_freiburg3_long_office_household/rgb/1341848053.082651.png",
    "image_key": 2146,
    "pose": [
        -0.3505,
        1.7106,
        1.4218,
        -0.1457,
        0.8197,
        -0.5529,
        -0.0337
    ]
}