{
    "object_key": [
        33,
        22,
        24,
        23,
        0
    ],
    "bbox": [
        [
            70.60175323486328,
            269.2908935546875,
            116.17820739746094,
            369.2755126953125
        ],
        [
            0.0,
            113.23847198486328,
            127.01260375976562,
            334.1299133300781
        ],
        [
            17.647724151611328,
            416.2159729003906,
            77.23703002929688,
            469.805419921875
        ],
        [
            0.0,
            352.947265625,
            56.90087890625,
            430.8974609375
        ],
        [
            333.39801025390625,
            0.0,
            433.1828308105469,
            99.4752426147461
        ]
    ],
    "score": [
        0.7835928797721863,
        0.8782100677490234,
        0.9707750678062439,
        0.6795562505722046,
        0.9338571429252625
    ],
    "label": [
        39,
        56,
        64,
        66,
        72
    ],
    "image_path": "rgbd_dataset_freiburg3_long_office_household/rgb/1341848002.474697.png",
    "image_key": 645,
    "pose": [
        0.787,
        -1.2051,
        1.4959,
        0.8601,
        0.0891,
        -0.0808,
        -0.4958
    ]
}