{
    "object_key": [
        5,
        3
    ],
    "bbox": [
        [
            429.02191162109375,
            34.856868743896484,
            473.5472412109375,
            164.84132385253906
        ],
        [
            461.0516662597656,
            43.34431457519531,
            528.27880859375,
            175.9315948486328
        ]
    ],
    "score": [
        0.9404935240745544,
        0.9337375164031982
    ],
    "label": [
        39,
        39
    ],
    "image_path": "rgbd_dataset_freiburg3_long_office_household/rgb/1341848052.074871.png",
    "image_key": 2116,
    "pose": [
        -0.1567,
        1.5492,
        1.4195,
        -0.1411,
        0.8172,
        -0.5567,
        0.0483
    ]
}