{
    "object_key": [
        20
    ],
    "bbox": [
        [
            184.1632843017578,
            13.602129936218262,
            570.2730102539062,
            479.9087829589844
        ]
    ],
    "score": [
        0.9862819314002991
    ],
    "label": [
        77
    ],
    "image_path": "rgbd_dataset_freiburg3_long_office_household/rgb/1341848016.757848.png",
    "image_key": 1070,
    "pose": [
        -1.0217,
        -1.1106,
        1.2213,
        0.6171,
        0.6535,
        -0.3168,
        -0.3028
    ]
}