{
    "object_key": [
        1,
        8
    ],
    "bbox": [
        [
            488.5829162597656,
            291.9476318359375,
            634.13525390625,
            476.3289489746094
        ],
        [
            246.61322021484375,
            20.399930953979492,
            397.05865478515625,
            180.03005981445312
        ]
    ],
    "score": [
        0.9198272824287415,
        0.9353922605514526
    ],
    "label": [
        56,
        74
    ],
    "image_path": "rgbd_dataset_freiburg3_long_office_household/rgb/1341847992.518735.png",
    "image_key": 351,
    "pose": [
        1.5365,
        0.7579,
        1.5821,
        0.4913,
        0.6901,
        -0.4321,
        -0.3093
    ]
}