{
    "object_key": [
        53,
        11,
        20
    ],
    "bbox": [
        [
            258.6943359375,
            92.58604431152344,
            303.28302001953125,
            206.68524169921875
        ],
        [
            112.12728881835938,
            65.46348571777344,
            151.11087036132812,
            154.09613037109375
        ],
        [
            449.4502868652344,
            0.913303017616272,
            544.2885131835938,
            108.49374389648438
        ]
    ],
    "score": [
        0.9607707858085632,
        0.9418453574180603,
        0.869279682636261
    ],
    "label": [
        39,
        39,
        77
    ],
    "image_path": "rgbd_dataset_freiburg3_long_office_household/rgb/1341848036.354859.png",
    "image_key": 1649,
    "pose": [
        -3.2296,
        0.6193,
        1.4325,
        -0.3946,
        0.7802,
        -0.3796,
        0.3024
    ]
}