{
    "object_key": [
        21,
        28,
        42,
        20
    ],
    "bbox": [
        [
            260.3396301269531,
            211.09059143066406,
            500.24908447265625,
            470.0152893066406
        ],
        [
            503.6826477050781,
            15.871786117553711,
            637.0111083984375,
            172.31813049316406
        ],
        [
            479.3878479003906,
            151.7997589111328,
            640.0,
            218.94424438476562
        ],
        [
            261.0921630859375,
            102.9032974243164,
            497.232177734375,
            381.7448425292969
        ]
    ],
    "score": [
        0.9963873624801636,
        0.9693284034729004,
        0.981357753276825,
        0.9219815135002136
    ],
    "label": [
        56,
        62,
        66,
        77
    ],
    "image_path": "rgbd_dataset_freiburg3_long_office_household/rgb/1341848020.271152.png",
    "image_key": 1174,
    "pose": [
        -0.8402,
        -1.8773,
        1.3287,
        0.8024,
        0.3239,
        -0.1975,
        -0.4608
    ]
}