{
    "object_key": [
        1
    ],
    "bbox": [
        [
            486.5828552246094,
            178.19918823242188,
            636.1572875976562,
            407.93829345703125
        ]
    ],
    "score": [
        0.9900740385055542
    ],
    "label": [
        56
    ],
    "image_path": "rgbd_dataset_freiburg3_long_office_household/rgb/1341847995.566681.png",
    "image_key": 441,
    "pose": [
        1.8028,
        -0.1346,
        1.5865,
        0.6368,
        0.5555,
        -0.3589,
        -0.3963
    ]
}