{
    "object_key": [
        53,
        14,
        15,
        9
    ],
    "bbox": [
        [
            187.99855041503906,
            39.79916763305664,
            239.1837158203125,
            172.29969787597656
        ],
        [
            0.0,
            182.54794311523438,
            31.829702377319336,
            268.3409423828125
        ],
        [
            166.12216186523438,
            254.93894958496094,
            223.0276336669922,
            318.1673583984375
        ],
        [
            243.4122314453125,
            236.39654541015625,
            308.30194091796875,
            258.9193115234375
        ]
    ],
    "score": [
        0.8078342080116272,
        0.5134130716323853,
        0.5433197617530823,
        0.5618140697479248
    ],
    "label": [
        39,
        39,
        41,
        44
    ],
    "image_path": "rgbd_dataset_freiburg3_long_office_household/rgb/1341848044.870686.png",
    "image_key": 1901,
    "pose": [
        -1.662,
        1.5021,
        1.433,
        0.2498,
        0.8591,
        -0.4463,
        -0.0215
    ]
}