{
    "object_key": [
        28,
        22,
        38,
        42
    ],
    "bbox": [
        [
            325.0204772949219,
            13.585286140441895,
            427.6420593261719,
            200.86083984375
        ],
        [
            464.3318786621094,
            0.0,
            543.2861938476562,
            93.68358612060547
        ],
        [
            525.4925537109375,
            152.31800842285156,
            567.7653198242188,
            174.24742126464844
        ],
        [
            396.5538330078125,
            153.0734100341797,
            498.21728515625,
            242.1194305419922
        ]
    ],
    "score": [
        0.9962735176086426,
        0.9391254186630249,
        0.9968908429145813,
        0.9985920786857605
    ],
    "label": [
        62,
        62,
        64,
        66
    ],
    "image_path": "rgbd_dataset_freiburg3_long_office_household/rgb/1341848029.118800.png",
    "image_key": 1435,
    "pose": [
        -2.6044,
        -0.8442,
        1.3835,
        0.7521,
        -0.4476,
        0.2097,
        -0.436
    ]
}